pymacros4py/__init__.py
pymacros4py/_evaluator.py
pymacros4py/_files.py
pymacros4py/_global_evaluation_context.py
pymacros4py/_pre_processor.py
pymacros4py/_template_script.py
pymacros4py/_tokenizer.py
pymacros4py/py.typed
pymacros4py-0.8.3.dist-info/licenses/LICENSE
pymacros4py-0.8.3.dist-info/METADATA
pymacros4py-0.8.3.dist-info/WHEEL
pymacros4py-0.8.3.dist-info/top_level.txt
pymacros4py-0.8.3.dist-info/RECORD
