Metadata-Version: 2.4
Name: pymacros4py
Version: 0.8.3
Summary: pymacros4py is a templating system for Python code. It is based on a source-level macro preprocessor. Expressions, statements, and functions in the macro domain are also written in Python.
Author-email: "Dr. Helmut Melcher" <HeWeMel@web.de>
Project-URL: Homepage, https://github.com/hewemel/pymacros4py
Project-URL: Repository, https://github.com/hewemel/pymacros4py.git
Project-URL: Issues, https://github.com/hewemel/pymacros4py/issues
Keywords: macro,preprocessor,source-level,python code,replace,template
Classifier: Development Status :: 5 - Production/Stable
Classifier: License :: OSI Approved :: MIT License
Classifier: Programming Language :: Python :: 3
Classifier: Programming Language :: Python :: 3.10
Classifier: Programming Language :: Python :: 3.11
Classifier: Programming Language :: Python :: 3.12
Classifier: Programming Language :: Python :: 3.13
Classifier: Programming Language :: Python :: Implementation :: CPython
Classifier: Programming Language :: Python :: Implementation :: PyPy
Classifier: Intended Audience :: Developers
Classifier: Operating System :: OS Independent
Classifier: Topic :: Software Development :: Libraries :: Python Modules
Classifier: Typing :: Typed
Requires-Python: >=3.10
License-File: LICENSE
Dynamic: license-file
